HISTORY.rst
LICENSE
MANIFEST.in
README-ja.rst
README.md
README.rst
setup.cfg
setup.py
tox.ini
django_subcommand.egg-info/PKG-INFO
django_subcommand.egg-info/SOURCES.txt
django_subcommand.egg-info/dependency_links.txt
django_subcommand.egg-info/requires.txt
django_subcommand.egg-info/top_level.txt
docs/Makefile
docs/make.bat
docs/build/doctrees/base.doctree
docs/build/doctrees/environment.pickle
docs/build/doctrees/generate.doctree
docs/build/doctrees/index.doctree
docs/build/doctrees/manager.doctree
docs/build/doctrees/startsubcommand.doctree
docs/build/doctrees/template.doctree
docs/build/doctrees/usage.doctree
docs/build/html/.buildinfo
docs/build/html/base.html
docs/build/html/generate.html
docs/build/html/genindex.html
docs/build/html/index.html
docs/build/html/manager.html
docs/build/html/objects.inv
docs/build/html/py-modindex.html
docs/build/html/search.html
docs/build/html/searchindex.js
docs/build/html/startsubcommand.html
docs/build/html/template.html
docs/build/html/usage.html
docs/build/html/_modules/index.html
docs/build/html/_modules/subcommand/management/base.html
docs/build/html/_modules/subcommand/management/generate.html
docs/build/html/_modules/subcommand/management/commands/startsubcommand.html
docs/build/html/_sources/base.txt
docs/build/html/_sources/generate.txt
docs/build/html/_sources/index.txt
docs/build/html/_sources/manager.txt
docs/build/html/_sources/startsubcommand.txt
docs/build/html/_sources/template.txt
docs/build/html/_sources/usage.txt
docs/build/html/_static/ajax-loader.gif
docs/build/html/_static/basic.css
docs/build/html/_static/comment-bright.png
docs/build/html/_static/comment-close.png
docs/build/html/_static/comment.png
docs/build/html/_static/default.css
docs/build/html/_static/dialog-note.png
docs/build/html/_static/dialog-seealso.png
docs/build/html/_static/dialog-topic.png
docs/build/html/_static/dialog-warning.png
docs/build/html/_static/doctools.js
docs/build/html/_static/down-pressed.png
docs/build/html/_static/down.png
docs/build/html/_static/epub.css
docs/build/html/_static/file.png
docs/build/html/_static/footerbg.png
docs/build/html/_static/headerbg.png
docs/build/html/_static/ie6.css
